JsMeetsStarlette/JsPyBackground.py
JsMeetsStarlette/JsPyBinarySocket.py
JsMeetsStarlette/JsPyFunction.py
JsMeetsStarlette/JsPyPubsub.py
JsMeetsStarlette/JsPyQueue.py
JsMeetsStarlette/JsPyTextSocket.py
JsMeetsStarlette/__init__.py
JsMeetsStarlette-0.0.1.dist-info/LICENSE
JsMeetsStarlette-0.0.1.dist-info/METADATA
JsMeetsStarlette-0.0.1.dist-info/WHEEL
JsMeetsStarlette-0.0.1.dist-info/top_level.txt
JsMeetsStarlette-0.0.1.dist-info/RECORD
