Metadata-Version: 2.1
Name: JsMeetsStarlette
Version: 0.0.1
Summary: This is a library that bridges server-side python and browser-side javascript.
Home-page: https://github.com/meloncookie/JsMeetsStarlette
Author: meloncookie
Author-email: 
License: MIT
Platform: UNKNOWN
Classifier: Development Status :: 3 - Alpha
Classifier: Environment :: Web Environment
Classifier: Intended Audience :: Developers
Classifier: Programming Language :: Python :: 3
Classifier: Programming Language :: Python :: 3.7
Classifier: Programming Language :: Python :: 3.8
Classifier: License :: OSI Approved :: MIT License
Classifier: Operating System :: OS Independent
Classifier: Topic :: Internet :: WWW/HTTP
Requires-Python: >=3.7
Provides-Extra: full
Requires-Dist: aiofiles ; extra == 'full'
Requires-Dist: graphene ; extra == 'full'
Requires-Dist: itsdangerous ; extra == 'full'
Requires-Dist: jinja2 ; extra == 'full'
Requires-Dist: python-multipart ; extra == 'full'
Requires-Dist: pyyaml ; extra == 'full'
Requires-Dist: requests ; extra == 'full'
Requires-Dist: ujson ; extra == 'full'
Requires-Dist: starlette ; extra == 'full'
